lzc_bailian_mcp_server/__init__.py
lzc_bailian_mcp_server/server.py
lzc_bailian_mcp_server-0.1.0.dist-info/METADATA
lzc_bailian_mcp_server-0.1.0.dist-info/WHEEL
lzc_bailian_mcp_server-0.1.0.dist-info/entry_points.txt
lzc_bailian_mcp_server-0.1.0.dist-info/RECORD
