Metadata-Version: 2.4
Name: lzc-bailian-mcp-server
Version: 0.1.0
Summary: Add your description here
Requires-Python: >=3.12
Requires-Dist: bs4>=0.0.2
Requires-Dist: dashscope>=1.23.5
Requires-Dist: dotenv>=0.9.9
Requires-Dist: httpx>=0.28.1
Requires-Dist: mcp[cli]>=1.9.4
